project/__init__.py
project/engine/__init__.py
project/engine/data_engine.py
project/rds_uploader/__init__.py
project/rds_uploader/rds_module.py
testing/__init__.py
testing/rds_test.py
testing/scraper_test.py
fplengine-0.0.2.dist-info/LICENSE
fplengine-0.0.2.dist-info/METADATA
fplengine-0.0.2.dist-info/WHEEL
fplengine-0.0.2.dist-info/top_level.txt
fplengine-0.0.2.dist-info/RECORD
