Metadata-Version: 2.1
Name: fplengine
Version: 0.0.2
Summary: Package to pull fantasy football data and run your account
Home-page: https://github.com/HendoGit/FantasyFootyBot.git
Author: Alex Henderson
License: Apache
Platform: UNKNOWN
License-File: LICENSE
Requires-Dist: requests
Requires-Dist: sqlalchemy
Requires-Dist: psycopg2
Requires-Dist: pandas
